{
  "id": "74cdeec3-3b78-4628-a5fc-126f6b2952c4",
  "prevId": "00000000-0000-0000-0000-000000000000",
  "version": "7",
  "dialect": "postgresql",
  "tables": {
    "public.activity_recommendation_logs": {
      "name": "activity_recommendation_logs",
      "schema": "",
      "columns": {
        "id": {
          "name": "id",
          "type": "serial",
          "primaryKey": true,
          "notNull": true
        },
        "user_id": {
          "name": "user_id",
          "type": "integer",
          "primaryKey": false,
          "notNull": true
        },
        "destination": {
          "name": "destination",
          "type": "varchar(255)",
          "primaryKey": false,
          "notNull": true
        },
        "budget": {
          "name": "budget",
          "type": "numeric(10, 2)",
          "primaryKey": false,
          "notNull": false
        },
        "interests": {
          "name": "interests",
          "type": "json",
          "primaryKey": false,
          "notNull": false
        },
        "recommendations": {
          "name": "recommendations",
          "type": "json",
          "primaryKey": false,
          "notNull": false
        },
        "created_at": {
          "name": "created_at",
          "type": "timestamp",
          "primaryKey": false,
          "notNull": true,
          "default": "now()"
        }
      },
      "indexes": {
        "activity_logs_user_idx": {
          "name": "activity_logs_user_idx",
          "columns": [
            {
              "expression": "user_id",
              "isExpression": false,
              "asc": true,
              "nulls": "last"
            }
          ],
          "isUnique": false,
          "concurrently": false,
          "method": "btree",
          "with": {}
        },
        "activity_logs_destination_idx": {
          "name": "activity_logs_destination_idx",
          "columns": [
            {
              "expression": "destination",
              "isExpression": false,
              "asc": true,
              "nulls": "last"
            }
          ],
          "isUnique": false,
          "concurrently": false,
          "method": "btree",
          "with": {}
        },
        "activity_logs_date_idx": {
          "name": "activity_logs_date_idx",
          "columns": [
            {
              "expression": "created_at",
              "isExpression": false,
              "asc": true,
              "nulls": "last"
            }
          ],
          "isUnique": false,
          "concurrently": false,
          "method": "btree",
          "with": {}
        }
      },
      "foreignKeys": {
        "activity_recommendation_logs_user_id_users_id_fk": {
          "name": "activity_recommendation_logs_user_id_users_id_fk",
          "tableFrom": "activity_recommendation_logs",
          "tableTo": "users",
          "columnsFrom": [
            "user_id"
          ],
          "columnsTo": [
            "id"
          ],
          "onDelete": "no action",
          "onUpdate": "no action"
        }
      },
      "compositePrimaryKeys": {},
      "uniqueConstraints": {},
      "policies": {},
      "checkConstraints": {},
      "isRLSEnabled": false
    },
    "public.agent_performance_logs": {
      "name": "agent_performance_logs",
      "schema": "",
      "columns": {
        "id": {
          "name": "id",
          "type": "serial",
          "primaryKey": true,
          "notNull": true
        },
        "agent_id": {
          "name": "agent_id",
          "type": "integer",
          "primaryKey": false,
          "notNull": true
        },
        "total_bookings": {
          "name": "total_bookings",
          "type": "integer",
          "primaryKey": false,
          "notNull": true,
          "default": 0
        },
        "total_revenue": {
          "name": "total_revenue",
          "type": "numeric(12, 2)",
          "primaryKey": false,
          "notNull": true,
          "default": "'0'"
        },
        "average_rating": {
          "name": "average_rating",
          "type": "numeric(3, 2)",
          "primaryKey": false,
          "notNull": false,
          "default": "'0'"
        },
        "ranking_position": {
          "name": "ranking_position",
          "type": "integer",
          "primaryKey": false,
          "notNull": false
        },
        "calculated_at": {
          "name": "calculated_at",
          "type": "timestamp",
          "primaryKey": false,
          "notNull": true,
          "default": "now()"
        }
      },
      "indexes": {
        "agent_performance_agent_idx": {
          "name": "agent_performance_agent_idx",
          "columns": [
            {
              "expression": "agent_id",
              "isExpression": false,
              "asc": true,
              "nulls": "last"
            }
          ],
          "isUnique": false,
          "concurrently": false,
          "method": "btree",
          "with": {}
        },
        "agent_performance_ranking_idx": {
          "name": "agent_performance_ranking_idx",
          "columns": [
            {
              "expression": "ranking_position",
              "isExpression": false,
              "asc": true,
              "nulls": "last"
            }
          ],
          "isUnique": false,
          "concurrently": false,
          "method": "btree",
          "with": {}
        },
        "agent_performance_date_idx": {
          "name": "agent_performance_date_idx",
          "columns": [
            {
              "expression": "calculated_at",
              "isExpression": false,
              "asc": true,
              "nulls": "last"
            }
          ],
          "isUnique": false,
          "concurrently": false,
          "method": "btree",
          "with": {}
        }
      },
      "foreignKeys": {
        "agent_performance_logs_agent_id_users_id_fk": {
          "name": "agent_performance_logs_agent_id_users_id_fk",
          "tableFrom": "agent_performance_logs",
          "tableTo": "users",
          "columnsFrom": [
            "agent_id"
          ],
          "columnsTo": [
            "id"
          ],
          "onDelete": "no action",
          "onUpdate": "no action"
        }
      },
      "compositePrimaryKeys": {},
      "uniqueConstraints": {},
      "policies": {},
      "checkConstraints": {},
      "isRLSEnabled": false
    },
    "public.audit_logs": {
      "name": "audit_logs",
      "schema": "",
      "columns": {
        "id": {
          "name": "id",
          "type": "serial",
          "primaryKey": true,
          "notNull": true
        },
        "user_id": {
          "name": "user_id",
          "type": "integer",
          "primaryKey": false,
          "notNull": false
        },
        "action": {
          "name": "action",
          "type": "varchar(255)",
          "primaryKey": false,
          "notNull": true
        },
        "table_name": {
          "name": "table_name",
          "type": "varchar(100)",
          "primaryKey": false,
          "notNull": true
        },
        "record_id": {
          "name": "record_id",
          "type": "integer",
          "primaryKey": false,
          "notNull": false
        },
        "old_values": {
          "name": "old_values",
          "type": "json",
          "primaryKey": false,
          "notNull": false
        },
        "new_values": {
          "name": "new_values",
          "type": "json",
          "primaryKey": false,
          "notNull": false
        },
        "ip_address": {
          "name": "ip_address",
          "type": "varchar(45)",
          "primaryKey": false,
          "notNull": false
        },
        "user_agent": {
          "name": "user_agent",
          "type": "varchar(500)",
          "primaryKey": false,
          "notNull": false
        },
        "created_at": {
          "name": "created_at",
          "type": "timestamp",
          "primaryKey": false,
          "notNull": true,
          "default": "now()"
        }
      },
      "indexes": {
        "audit_logs_user_idx": {
          "name": "audit_logs_user_idx",
          "columns": [
            {
              "expression": "user_id",
              "isExpression": false,
              "asc": true,
              "nulls": "last"
            }
          ],
          "isUnique": false,
          "concurrently": false,
          "method": "btree",
          "with": {}
        },
        "audit_logs_table_idx": {
          "name": "audit_logs_table_idx",
          "columns": [
            {
              "expression": "table_name",
              "isExpression": false,
              "asc": true,
              "nulls": "last"
            }
          ],
          "isUnique": false,
          "concurrently": false,
          "method": "btree",
          "with": {}
        },
        "audit_logs_action_idx": {
          "name": "audit_logs_action_idx",
          "columns": [
            {
              "expression": "action",
              "isExpression": false,
              "asc": true,
              "nulls": "last"
            }
          ],
          "isUnique": false,
          "concurrently": false,
          "method": "btree",
          "with": {}
        },
        "audit_logs_date_idx": {
          "name": "audit_logs_date_idx",
          "columns": [
            {
              "expression": "created_at",
              "isExpression": false,
              "asc": true,
              "nulls": "last"
            }
          ],
          "isUnique": false,
          "concurrently": false,
          "method": "btree",
          "with": {}
        }
      },
      "foreignKeys": {
        "audit_logs_user_id_users_id_fk": {
          "name": "audit_logs_user_id_users_id_fk",
          "tableFrom": "audit_logs",
          "tableTo": "users",
          "columnsFrom": [
            "user_id"
          ],
          "columnsTo": [
            "id"
          ],
          "onDelete": "no action",
          "onUpdate": "no action"
        }
      },
      "compositePrimaryKeys": {},
      "uniqueConstraints": {},
      "policies": {},
      "checkConstraints": {},
      "isRLSEnabled": false
    },
    "public.bookings": {
      "name": "bookings",
      "schema": "",
      "columns": {
        "id": {
          "name": "id",
          "type": "serial",
          "primaryKey": true,
          "notNull": true
        },
        "client_id": {
          "name": "client_id",
          "type": "integer",
          "primaryKey": false,
          "notNull": true
        },
        "trip_id": {
          "name": "trip_id",
          "type": "integer",
          "primaryKey": false,
          "notNull": true
        },
        "seats_booked": {
          "name": "seats_booked",
          "type": "integer",
          "primaryKey": false,
          "notNull": true
        },
        "total_price": {
          "name": "total_price",
          "type": "numeric(10, 2)",
          "primaryKey": false,
          "notNull": true
        },
        "status": {
          "name": "status",
          "type": "booking_status",
          "typeSchema": "public",
          "primaryKey": false,
          "notNull": true,
          "default": "'pending'"
        },
        "payment_status": {
          "name": "payment_status",
          "type": "payment_status",
          "typeSchema": "public",
          "primaryKey": false,
          "notNull": true,
          "default": "'pending'"
        },
        "payment_reference": {
          "name": "payment_reference",
          "type": "varchar(255)",
          "primaryKey": false,
          "notNull": false
        },
        "booking_date": {
          "name": "booking_date",
          "type": "timestamp",
          "primaryKey": false,
          "notNull": true,
          "default": "now()"
        },
        "cancellation_date": {
          "name": "cancellation_date",
          "type": "timestamp",
          "primaryKey": false,
          "notNull": false
        },
        "cancellation_reason": {
          "name": "cancellation_reason",
          "type": "text",
          "primaryKey": false,
          "notNull": false
        },
        "created_at": {
          "name": "created_at",
          "type": "timestamp",
          "primaryKey": false,
          "notNull": true,
          "default": "now()"
        },
        "updated_at": {
          "name": "updated_at",
          "type": "timestamp",
          "primaryKey": false,
          "notNull": true,
          "default": "now()"
        }
      },
      "indexes": {
        "bookings_client_idx": {
          "name": "bookings_client_idx",
          "columns": [
            {
              "expression": "client_id",
              "isExpression": false,
              "asc": true,
              "nulls": "last"
            }
          ],
          "isUnique": false,
          "concurrently": false,
          "method": "btree",
          "with": {}
        },
        "bookings_trip_idx": {
          "name": "bookings_trip_idx",
          "columns": [
            {
              "expression": "trip_id",
              "isExpression": false,
              "asc": true,
              "nulls": "last"
            }
          ],
          "isUnique": false,
          "concurrently": false,
          "method": "btree",
          "with": {}
        },
        "bookings_status_idx": {
          "name": "bookings_status_idx",
          "columns": [
            {
              "expression": "status",
              "isExpression": false,
              "asc": true,
              "nulls": "last"
            }
          ],
          "isUnique": false,
          "concurrently": false,
          "method": "btree",
          "with": {}
        },
        "bookings_date_idx": {
          "name": "bookings_date_idx",
          "columns": [
            {
              "expression": "booking_date",
              "isExpression": false,
              "asc": true,
              "nulls": "last"
            }
          ],
          "isUnique": false,
          "concurrently": false,
          "method": "btree",
          "with": {}
        }
      },
      "foreignKeys": {
        "bookings_client_id_users_id_fk": {
          "name": "bookings_client_id_users_id_fk",
          "tableFrom": "bookings",
          "tableTo": "users",
          "columnsFrom": [
            "client_id"
          ],
          "columnsTo": [
            "id"
          ],
          "onDelete": "no action",
          "onUpdate": "no action"
        },
        "bookings_trip_id_trips_id_fk": {
          "name": "bookings_trip_id_trips_id_fk",
          "tableFrom": "bookings",
          "tableTo": "trips",
          "columnsFrom": [
            "trip_id"
          ],
          "columnsTo": [
            "id"
          ],
          "onDelete": "no action",
          "onUpdate": "no action"
        }
      },
      "compositePrimaryKeys": {},
      "uniqueConstraints": {},
      "policies": {},
      "checkConstraints": {},
      "isRLSEnabled": false
    },
    "public.contact_messages": {
      "name": "contact_messages",
      "schema": "",
      "columns": {
        "id": {
          "name": "id",
          "type": "serial",
          "primaryKey": true,
          "notNull": true
        },
        "user_id": {
          "name": "user_id",
          "type": "integer",
          "primaryKey": false,
          "notNull": false
        },
        "name": {
          "name": "name",
          "type": "varchar(255)",
          "primaryKey": false,
          "notNull": true
        },
        "email": {
          "name": "email",
          "type": "varchar(255)",
          "primaryKey": false,
          "notNull": true
        },
        "subject": {
          "name": "subject",
          "type": "varchar(255)",
          "primaryKey": false,
          "notNull": true
        },
        "message": {
          "name": "message",
          "type": "text",
          "primaryKey": false,
          "notNull": true
        },
        "status": {
          "name": "status",
          "type": "message_status",
          "typeSchema": "public",
          "primaryKey": false,
          "notNull": true,
          "default": "'new'"
        },
        "assigned_admin_id": {
          "name": "assigned_admin_id",
          "type": "integer",
          "primaryKey": false,
          "notNull": false
        },
        "created_at": {
          "name": "created_at",
          "type": "timestamp",
          "primaryKey": false,
          "notNull": true,
          "default": "now()"
        },
        "updated_at": {
          "name": "updated_at",
          "type": "timestamp",
          "primaryKey": false,
          "notNull": true,
          "default": "now()"
        }
      },
      "indexes": {
        "contact_messages_user_idx": {
          "name": "contact_messages_user_idx",
          "columns": [
            {
              "expression": "user_id",
              "isExpression": false,
              "asc": true,
              "nulls": "last"
            }
          ],
          "isUnique": false,
          "concurrently": false,
          "method": "btree",
          "with": {}
        },
        "contact_messages_status_idx": {
          "name": "contact_messages_status_idx",
          "columns": [
            {
              "expression": "status",
              "isExpression": false,
              "asc": true,
              "nulls": "last"
            }
          ],
          "isUnique": false,
          "concurrently": false,
          "method": "btree",
          "with": {}
        },
        "contact_messages_admin_idx": {
          "name": "contact_messages_admin_idx",
          "columns": [
            {
              "expression": "assigned_admin_id",
              "isExpression": false,
              "asc": true,
              "nulls": "last"
            }
          ],
          "isUnique": false,
          "concurrently": false,
          "method": "btree",
          "with": {}
        }
      },
      "foreignKeys": {
        "contact_messages_user_id_users_id_fk": {
          "name": "contact_messages_user_id_users_id_fk",
          "tableFrom": "contact_messages",
          "tableTo": "users",
          "columnsFrom": [
            "user_id"
          ],
          "columnsTo": [
            "id"
          ],
          "onDelete": "no action",
          "onUpdate": "no action"
        },
        "contact_messages_assigned_admin_id_users_id_fk": {
          "name": "contact_messages_assigned_admin_id_users_id_fk",
          "tableFrom": "contact_messages",
          "tableTo": "users",
          "columnsFrom": [
            "assigned_admin_id"
          ],
          "columnsTo": [
            "id"
          ],
          "onDelete": "no action",
          "onUpdate": "no action"
        }
      },
      "compositePrimaryKeys": {},
      "uniqueConstraints": {},
      "policies": {},
      "checkConstraints": {},
      "isRLSEnabled": false
    },
    "public.custom_trip_requests": {
      "name": "custom_trip_requests",
      "schema": "",
      "columns": {
        "id": {
          "name": "id",
          "type": "serial",
          "primaryKey": true,
          "notNull": true
        },
        "client_id": {
          "name": "client_id",
          "type": "integer",
          "primaryKey": false,
          "notNull": true
        },
        "assigned_agent_id": {
          "name": "assigned_agent_id",
          "type": "integer",
          "primaryKey": false,
          "notNull": false
        },
        "destination": {
          "name": "destination",
          "type": "varchar(255)",
          "primaryKey": false,
          "notNull": true
        },
        "budget": {
          "name": "budget",
          "type": "numeric(10, 2)",
          "primaryKey": false,
          "notNull": true
        },
        "interests": {
          "name": "interests",
          "type": "text",
          "primaryKey": false,
          "notNull": false
        },
        "preferred_start_date": {
          "name": "preferred_start_date",
          "type": "date",
          "primaryKey": false,
          "notNull": false
        },
        "preferred_end_date": {
          "name": "preferred_end_date",
          "type": "date",
          "primaryKey": false,
          "notNull": false
        },
        "group_size": {
          "name": "group_size",
          "type": "integer",
          "primaryKey": false,
          "notNull": false,
          "default": 1
        },
        "status": {
          "name": "status",
          "type": "custom_trip_status",
          "typeSchema": "public",
          "primaryKey": false,
          "notNull": true,
          "default": "'pending'"
        },
        "client_notes": {
          "name": "client_notes",
          "type": "text",
          "primaryKey": false,
          "notNull": false
        },
        "agent_response": {
          "name": "agent_response",
          "type": "text",
          "primaryKey": false,
          "notNull": false
        },
        "quoted_price": {
          "name": "quoted_price",
          "type": "numeric(10, 2)",
          "primaryKey": false,
          "notNull": false
        },
        "created_at": {
          "name": "created_at",
          "type": "timestamp",
          "primaryKey": false,
          "notNull": true,
          "default": "now()"
        },
        "updated_at": {
          "name": "updated_at",
          "type": "timestamp",
          "primaryKey": false,
          "notNull": true,
          "default": "now()"
        }
      },
      "indexes": {
        "custom_trips_client_idx": {
          "name": "custom_trips_client_idx",
          "columns": [
            {
              "expression": "client_id",
              "isExpression": false,
              "asc": true,
              "nulls": "last"
            }
          ],
          "isUnique": false,
          "concurrently": false,
          "method": "btree",
          "with": {}
        },
        "custom_trips_agent_idx": {
          "name": "custom_trips_agent_idx",
          "columns": [
            {
              "expression": "assigned_agent_id",
              "isExpression": false,
              "asc": true,
              "nulls": "last"
            }
          ],
          "isUnique": false,
          "concurrently": false,
          "method": "btree",
          "with": {}
        },
        "custom_trips_status_idx": {
          "name": "custom_trips_status_idx",
          "columns": [
            {
              "expression": "status",
              "isExpression": false,
              "asc": true,
              "nulls": "last"
            }
          ],
          "isUnique": false,
          "concurrently": false,
          "method": "btree",
          "with": {}
        },
        "custom_trips_destination_idx": {
          "name": "custom_trips_destination_idx",
          "columns": [
            {
              "expression": "destination",
              "isExpression": false,
              "asc": true,
              "nulls": "last"
            }
          ],
          "isUnique": false,
          "concurrently": false,
          "method": "btree",
          "with": {}
        }
      },
      "foreignKeys": {
        "custom_trip_requests_client_id_users_id_fk": {
          "name": "custom_trip_requests_client_id_users_id_fk",
          "tableFrom": "custom_trip_requests",
          "tableTo": "users",
          "columnsFrom": [
            "client_id"
          ],
          "columnsTo": [
            "id"
          ],
          "onDelete": "no action",
          "onUpdate": "no action"
        },
        "custom_trip_requests_assigned_agent_id_users_id_fk": {
          "name": "custom_trip_requests_assigned_agent_id_users_id_fk",
          "tableFrom": "custom_trip_requests",
          "tableTo": "users",
          "columnsFrom": [
            "assigned_agent_id"
          ],
          "columnsTo": [
            "id"
          ],
          "onDelete": "no action",
          "onUpdate": "no action"
        }
      },
      "compositePrimaryKeys": {},
      "uniqueConstraints": {},
      "policies": {},
      "checkConstraints": {},
      "isRLSEnabled": false
    },
    "public.email_verifications": {
      "name": "email_verifications",
      "schema": "",
      "columns": {
        "id": {
          "name": "id",
          "type": "serial",
          "primaryKey": true,
          "notNull": true
        },
        "user_id": {
          "name": "user_id",
          "type": "integer",
          "primaryKey": false,
          "notNull": true
        },
        "verification_code": {
          "name": "verification_code",
          "type": "varchar(10)",
          "primaryKey": false,
          "notNull": true
        },
        "verified": {
          "name": "verified",
          "type": "boolean",
          "primaryKey": false,
          "notNull": true,
          "default": false
        },
        "expires_at": {
          "name": "expires_at",
          "type": "timestamp",
          "primaryKey": false,
          "notNull": true
        },
        "created_at": {
          "name": "created_at",
          "type": "timestamp",
          "primaryKey": false,
          "notNull": true,
          "default": "now()"
        },
        "verified_at": {
          "name": "verified_at",
          "type": "timestamp",
          "primaryKey": false,
          "notNull": false
        }
      },
      "indexes": {
        "email_verifications_user_idx": {
          "name": "email_verifications_user_idx",
          "columns": [
            {
              "expression": "user_id",
              "isExpression": false,
              "asc": true,
              "nulls": "last"
            }
          ],
          "isUnique": false,
          "concurrently": false,
          "method": "btree",
          "with": {}
        },
        "email_verifications_code_idx": {
          "name": "email_verifications_code_idx",
          "columns": [
            {
              "expression": "verification_code",
              "isExpression": false,
              "asc": true,
              "nulls": "last"
            }
          ],
          "isUnique": false,
          "concurrently": false,
          "method": "btree",
          "with": {}
        }
      },
      "foreignKeys": {
        "email_verifications_user_id_users_id_fk": {
          "name": "email_verifications_user_id_users_id_fk",
          "tableFrom": "email_verifications",
          "tableTo": "users",
          "columnsFrom": [
            "user_id"
          ],
          "columnsTo": [
            "id"
          ],
          "onDelete": "no action",
          "onUpdate": "no action"
        }
      },
      "compositePrimaryKeys": {},
      "uniqueConstraints": {},
      "policies": {},
      "checkConstraints": {},
      "isRLSEnabled": false
    },
    "public.job_applications": {
      "name": "job_applications",
      "schema": "",
      "columns": {
        "id": {
          "name": "id",
          "type": "serial",
          "primaryKey": true,
          "notNull": true
        },
        "job_id": {
          "name": "job_id",
          "type": "integer",
          "primaryKey": false,
          "notNull": true
        },
        "applicant_id": {
          "name": "applicant_id",
          "type": "integer",
          "primaryKey": false,
          "notNull": true
        },
        "status": {
          "name": "status",
          "type": "application_status",
          "typeSchema": "public",
          "primaryKey": false,
          "notNull": true,
          "default": "'pending'"
        },
        "cover_letter": {
          "name": "cover_letter",
          "type": "text",
          "primaryKey": false,
          "notNull": false
        },
        "portfolio_links": {
          "name": "portfolio_links",
          "type": "json",
          "primaryKey": false,
          "notNull": false
        },
        "applied_at": {
          "name": "applied_at",
          "type": "timestamp",
          "primaryKey": false,
          "notNull": true,
          "default": "now()"
        },
        "status_updated_at": {
          "name": "status_updated_at",
          "type": "timestamp",
          "primaryKey": false,
          "notNull": true,
          "default": "now()"
        },
        "feedback": {
          "name": "feedback",
          "type": "text",
          "primaryKey": false,
          "notNull": false
        }
      },
      "indexes": {
        "job_applications_job_idx": {
          "name": "job_applications_job_idx",
          "columns": [
            {
              "expression": "job_id",
              "isExpression": false,
              "asc": true,
              "nulls": "last"
            }
          ],
          "isUnique": false,
          "concurrently": false,
          "method": "btree",
          "with": {}
        },
        "job_applications_applicant_idx": {
          "name": "job_applications_applicant_idx",
          "columns": [
            {
              "expression": "applicant_id",
              "isExpression": false,
              "asc": true,
              "nulls": "last"
            }
          ],
          "isUnique": false,
          "concurrently": false,
          "method": "btree",
          "with": {}
        },
        "job_applications_status_idx": {
          "name": "job_applications_status_idx",
          "columns": [
            {
              "expression": "status",
              "isExpression": false,
              "asc": true,
              "nulls": "last"
            }
          ],
          "isUnique": false,
          "concurrently": false,
          "method": "btree",
          "with": {}
        }
      },
      "foreignKeys": {
        "job_applications_job_id_jobs_id_fk": {
          "name": "job_applications_job_id_jobs_id_fk",
          "tableFrom": "job_applications",
          "tableTo": "jobs",
          "columnsFrom": [
            "job_id"
          ],
          "columnsTo": [
            "id"
          ],
          "onDelete": "no action",
          "onUpdate": "no action"
        },
        "job_applications_applicant_id_users_id_fk": {
          "name": "job_applications_applicant_id_users_id_fk",
          "tableFrom": "job_applications",
          "tableTo": "users",
          "columnsFrom": [
            "applicant_id"
          ],
          "columnsTo": [
            "id"
          ],
          "onDelete": "no action",
          "onUpdate": "no action"
        }
      },
      "compositePrimaryKeys": {},
      "uniqueConstraints": {},
      "policies": {},
      "checkConstraints": {},
      "isRLSEnabled": false
    },
    "public.jobs": {
      "name": "jobs",
      "schema": "",
      "columns": {
        "id": {
          "name": "id",
          "type": "serial",
          "primaryKey": true,
          "notNull": true
        },
        "client_id": {
          "name": "client_id",
          "type": "integer",
          "primaryKey": false,
          "notNull": true
        },
        "custom_trip_id": {
          "name": "custom_trip_id",
          "type": "integer",
          "primaryKey": false,
          "notNull": false
        },
        "title": {
          "name": "title",
          "type": "varchar(255)",
          "primaryKey": false,
          "notNull": true
        },
        "description": {
          "name": "description",
          "type": "text",
          "primaryKey": false,
          "notNull": true
        },
        "token_cost": {
          "name": "token_cost",
          "type": "integer",
          "primaryKey": false,
          "notNull": true
        },
        "category": {
          "name": "category",
          "type": "varchar(100)",
          "primaryKey": false,
          "notNull": false
        },
        "location": {
          "name": "location",
          "type": "varchar(255)",
          "primaryKey": false,
          "notNull": false
        },
        "status": {
          "name": "status",
          "type": "job_status",
          "typeSchema": "public",
          "primaryKey": false,
          "notNull": true,
          "default": "'open'"
        },
        "application_deadline": {
          "name": "application_deadline",
          "type": "date",
          "primaryKey": false,
          "notNull": false
        },
        "created_at": {
          "name": "created_at",
          "type": "timestamp",
          "primaryKey": false,
          "notNull": true,
          "default": "now()"
        },
        "updated_at": {
          "name": "updated_at",
          "type": "timestamp",
          "primaryKey": false,
          "notNull": true,
          "default": "now()"
        },
        "deleted_at": {
          "name": "deleted_at",
          "type": "timestamp",
          "primaryKey": false,
          "notNull": false
        }
      },
      "indexes": {
        "jobs_client_idx": {
          "name": "jobs_client_idx",
          "columns": [
            {
              "expression": "client_id",
              "isExpression": false,
              "asc": true,
              "nulls": "last"
            }
          ],
          "isUnique": false,
          "concurrently": false,
          "method": "btree",
          "with": {}
        },
        "jobs_status_idx": {
          "name": "jobs_status_idx",
          "columns": [
            {
              "expression": "status",
              "isExpression": false,
              "asc": true,
              "nulls": "last"
            }
          ],
          "isUnique": false,
          "concurrently": false,
          "method": "btree",
          "with": {}
        },
        "jobs_category_idx": {
          "name": "jobs_category_idx",
          "columns": [
            {
              "expression": "category",
              "isExpression": false,
              "asc": true,
              "nulls": "last"
            }
          ],
          "isUnique": false,
          "concurrently": false,
          "method": "btree",
          "with": {}
        },
        "jobs_location_idx": {
          "name": "jobs_location_idx",
          "columns": [
            {
              "expression": "location",
              "isExpression": false,
              "asc": true,
              "nulls": "last"
            }
          ],
          "isUnique": false,
          "concurrently": false,
          "method": "btree",
          "with": {}
        }
      },
      "foreignKeys": {
        "jobs_client_id_users_id_fk": {
          "name": "jobs_client_id_users_id_fk",
          "tableFrom": "jobs",
          "tableTo": "users",
          "columnsFrom": [
            "client_id"
          ],
          "columnsTo": [
            "id"
          ],
          "onDelete": "no action",
          "onUpdate": "no action"
        },
        "jobs_custom_trip_id_custom_trip_requests_id_fk": {
          "name": "jobs_custom_trip_id_custom_trip_requests_id_fk",
          "tableFrom": "jobs",
          "tableTo": "custom_trip_requests",
          "columnsFrom": [
            "custom_trip_id"
          ],
          "columnsTo": [
            "id"
          ],
          "onDelete": "no action",
          "onUpdate": "no action"
        }
      },
      "compositePrimaryKeys": {},
      "uniqueConstraints": {},
      "policies": {},
      "checkConstraints": {},
      "isRLSEnabled": false
    },
    "public.notifications": {
      "name": "notifications",
      "schema": "",
      "columns": {
        "id": {
          "name": "id",
          "type": "serial",
          "primaryKey": true,
          "notNull": true
        },
        "user_id": {
          "name": "user_id",
          "type": "integer",
          "primaryKey": false,
          "notNull": true
        },
        "title": {
          "name": "title",
          "type": "varchar(255)",
          "primaryKey": false,
          "notNull": true
        },
        "message": {
          "name": "message",
          "type": "text",
          "primaryKey": false,
          "notNull": true
        },
        "type": {
          "name": "type",
          "type": "notification_type",
          "typeSchema": "public",
          "primaryKey": false,
          "notNull": true
        },
        "is_read": {
          "name": "is_read",
          "type": "boolean",
          "primaryKey": false,
          "notNull": true,
          "default": false
        },
        "metadata": {
          "name": "metadata",
          "type": "json",
          "primaryKey": false,
          "notNull": false
        },
        "created_at": {
          "name": "created_at",
          "type": "timestamp",
          "primaryKey": false,
          "notNull": true,
          "default": "now()"
        },
        "read_at": {
          "name": "read_at",
          "type": "timestamp",
          "primaryKey": false,
          "notNull": false
        }
      },
      "indexes": {
        "notifications_user_idx": {
          "name": "notifications_user_idx",
          "columns": [
            {
              "expression": "user_id",
              "isExpression": false,
              "asc": true,
              "nulls": "last"
            }
          ],
          "isUnique": false,
          "concurrently": false,
          "method": "btree",
          "with": {}
        },
        "notifications_type_idx": {
          "name": "notifications_type_idx",
          "columns": [
            {
              "expression": "type",
              "isExpression": false,
              "asc": true,
              "nulls": "last"
            }
          ],
          "isUnique": false,
          "concurrently": false,
          "method": "btree",
          "with": {}
        },
        "notifications_read_idx": {
          "name": "notifications_read_idx",
          "columns": [
            {
              "expression": "is_read",
              "isExpression": false,
              "asc": true,
              "nulls": "last"
            }
          ],
          "isUnique": false,
          "concurrently": false,
          "method": "btree",
          "with": {}
        }
      },
      "foreignKeys": {
        "notifications_user_id_users_id_fk": {
          "name": "notifications_user_id_users_id_fk",
          "tableFrom": "notifications",
          "tableTo": "users",
          "columnsFrom": [
            "user_id"
          ],
          "columnsTo": [
            "id"
          ],
          "onDelete": "no action",
          "onUpdate": "no action"
        }
      },
      "compositePrimaryKeys": {},
      "uniqueConstraints": {},
      "policies": {},
      "checkConstraints": {},
      "isRLSEnabled": false
    },
    "public.password_resets": {
      "name": "password_resets",
      "schema": "",
      "columns": {
        "id": {
          "name": "id",
          "type": "serial",
          "primaryKey": true,
          "notNull": true
        },
        "user_id": {
          "name": "user_id",
          "type": "integer",
          "primaryKey": false,
          "notNull": true
        },
        "token": {
          "name": "token",
          "type": "varchar(255)",
          "primaryKey": false,
          "notNull": true
        },
        "used": {
          "name": "used",
          "type": "boolean",
          "primaryKey": false,
          "notNull": true,
          "default": false
        },
        "expires_at": {
          "name": "expires_at",
          "type": "timestamp",
          "primaryKey": false,
          "notNull": true
        },
        "created_at": {
          "name": "created_at",
          "type": "timestamp",
          "primaryKey": false,
          "notNull": true,
          "default": "now()"
        }
      },
      "indexes": {
        "password_resets_user_idx": {
          "name": "password_resets_user_idx",
          "columns": [
            {
              "expression": "user_id",
              "isExpression": false,
              "asc": true,
              "nulls": "last"
            }
          ],
          "isUnique": false,
          "concurrently": false,
          "method": "btree",
          "with": {}
        },
        "password_resets_token_idx": {
          "name": "password_resets_token_idx",
          "columns": [
            {
              "expression": "token",
              "isExpression": false,
              "asc": true,
              "nulls": "last"
            }
          ],
          "isUnique": false,
          "concurrently": false,
          "method": "btree",
          "with": {}
        }
      },
      "foreignKeys": {
        "password_resets_user_id_users_id_fk": {
          "name": "password_resets_user_id_users_id_fk",
          "tableFrom": "password_resets",
          "tableTo": "users",
          "columnsFrom": [
            "user_id"
          ],
          "columnsTo": [
            "id"
          ],
          "onDelete": "no action",
          "onUpdate": "no action"
        }
      },
      "compositePrimaryKeys": {},
      "uniqueConstraints": {
        "password_resets_token_unique": {
          "name": "password_resets_token_unique",
          "nullsNotDistinct": false,
          "columns": [
            "token"
          ]
        }
      },
      "policies": {},
      "checkConstraints": {},
      "isRLSEnabled": false
    },
    "public.payments": {
      "name": "payments",
      "schema": "",
      "columns": {
        "id": {
          "name": "id",
          "type": "serial",
          "primaryKey": true,
          "notNull": true
        },
        "user_id": {
          "name": "user_id",
          "type": "integer",
          "primaryKey": false,
          "notNull": true
        },
        "reference_type": {
          "name": "reference_type",
          "type": "varchar(100)",
          "primaryKey": false,
          "notNull": true
        },
        "reference_id": {
          "name": "reference_id",
          "type": "integer",
          "primaryKey": false,
          "notNull": true
        },
        "amount": {
          "name": "amount",
          "type": "numeric(10, 2)",
          "primaryKey": false,
          "notNull": true
        },
        "currency": {
          "name": "currency",
          "type": "varchar(3)",
          "primaryKey": false,
          "notNull": true,
          "default": "'RWF'"
        },
        "status": {
          "name": "status",
          "type": "payment_status_enum",
          "typeSchema": "public",
          "primaryKey": false,
          "notNull": true,
          "default": "'pending'"
        },
        "gateway_reference": {
          "name": "gateway_reference",
          "type": "varchar(255)",
          "primaryKey": false,
          "notNull": false
        },
        "gateway_response": {
          "name": "gateway_response",
          "type": "json",
          "primaryKey": false,
          "notNull": false
        },
        "created_at": {
          "name": "created_at",
          "type": "timestamp",
          "primaryKey": false,
          "notNull": true,
          "default": "now()"
        },
        "updated_at": {
          "name": "updated_at",
          "type": "timestamp",
          "primaryKey": false,
          "notNull": true,
          "default": "now()"
        }
      },
      "indexes": {
        "payments_user_idx": {
          "name": "payments_user_idx",
          "columns": [
            {
              "expression": "user_id",
              "isExpression": false,
              "asc": true,
              "nulls": "last"
            }
          ],
          "isUnique": false,
          "concurrently": false,
          "method": "btree",
          "with": {}
        },
        "payments_reference_idx": {
          "name": "payments_reference_idx",
          "columns": [
            {
              "expression": "reference_type",
              "isExpression": false,
              "asc": true,
              "nulls": "last"
            },
            {
              "expression": "reference_id",
              "isExpression": false,
              "asc": true,
              "nulls": "last"
            }
          ],
          "isUnique": false,
          "concurrently": false,
          "method": "btree",
          "with": {}
        },
        "payments_status_idx": {
          "name": "payments_status_idx",
          "columns": [
            {
              "expression": "status",
              "isExpression": false,
              "asc": true,
              "nulls": "last"
            }
          ],
          "isUnique": false,
          "concurrently": false,
          "method": "btree",
          "with": {}
        }
      },
      "foreignKeys": {
        "payments_user_id_users_id_fk": {
          "name": "payments_user_id_users_id_fk",
          "tableFrom": "payments",
          "tableTo": "users",
          "columnsFrom": [
            "user_id"
          ],
          "columnsTo": [
            "id"
          ],
          "onDelete": "no action",
          "onUpdate": "no action"
        }
      },
      "compositePrimaryKeys": {},
      "uniqueConstraints": {},
      "policies": {},
      "checkConstraints": {},
      "isRLSEnabled": false
    },
    "public.reviews": {
      "name": "reviews",
      "schema": "",
      "columns": {
        "id": {
          "name": "id",
          "type": "serial",
          "primaryKey": true,
          "notNull": true
        },
        "client_id": {
          "name": "client_id",
          "type": "integer",
          "primaryKey": false,
          "notNull": true
        },
        "trip_id": {
          "name": "trip_id",
          "type": "integer",
          "primaryKey": false,
          "notNull": true
        },
        "booking_id": {
          "name": "booking_id",
          "type": "integer",
          "primaryKey": false,
          "notNull": true
        },
        "rating": {
          "name": "rating",
          "type": "integer",
          "primaryKey": false,
          "notNull": true
        },
        "comment": {
          "name": "comment",
          "type": "text",
          "primaryKey": false,
          "notNull": false
        },
        "status": {
          "name": "status",
          "type": "review_status",
          "typeSchema": "public",
          "primaryKey": false,
          "notNull": true,
          "default": "'active'"
        },
        "created_at": {
          "name": "created_at",
          "type": "timestamp",
          "primaryKey": false,
          "notNull": true,
          "default": "now()"
        },
        "updated_at": {
          "name": "updated_at",
          "type": "timestamp",
          "primaryKey": false,
          "notNull": true,
          "default": "now()"
        }
      },
      "indexes": {
        "reviews_client_idx": {
          "name": "reviews_client_idx",
          "columns": [
            {
              "expression": "client_id",
              "isExpression": false,
              "asc": true,
              "nulls": "last"
            }
          ],
          "isUnique": false,
          "concurrently": false,
          "method": "btree",
          "with": {}
        },
        "reviews_trip_idx": {
          "name": "reviews_trip_idx",
          "columns": [
            {
              "expression": "trip_id",
              "isExpression": false,
              "asc": true,
              "nulls": "last"
            }
          ],
          "isUnique": false,
          "concurrently": false,
          "method": "btree",
          "with": {}
        },
        "reviews_rating_idx": {
          "name": "reviews_rating_idx",
          "columns": [
            {
              "expression": "rating",
              "isExpression": false,
              "asc": true,
              "nulls": "last"
            }
          ],
          "isUnique": false,
          "concurrently": false,
          "method": "btree",
          "with": {}
        },
        "reviews_status_idx": {
          "name": "reviews_status_idx",
          "columns": [
            {
              "expression": "status",
              "isExpression": false,
              "asc": true,
              "nulls": "last"
            }
          ],
          "isUnique": false,
          "concurrently": false,
          "method": "btree",
          "with": {}
        }
      },
      "foreignKeys": {
        "reviews_client_id_users_id_fk": {
          "name": "reviews_client_id_users_id_fk",
          "tableFrom": "reviews",
          "tableTo": "users",
          "columnsFrom": [
            "client_id"
          ],
          "columnsTo": [
            "id"
          ],
          "onDelete": "no action",
          "onUpdate": "no action"
        },
        "reviews_trip_id_trips_id_fk": {
          "name": "reviews_trip_id_trips_id_fk",
          "tableFrom": "reviews",
          "tableTo": "trips",
          "columnsFrom": [
            "trip_id"
          ],
          "columnsTo": [
            "id"
          ],
          "onDelete": "no action",
          "onUpdate": "no action"
        },
        "reviews_booking_id_bookings_id_fk": {
          "name": "reviews_booking_id_bookings_id_fk",
          "tableFrom": "reviews",
          "tableTo": "bookings",
          "columnsFrom": [
            "booking_id"
          ],
          "columnsTo": [
            "id"
          ],
          "onDelete": "no action",
          "onUpdate": "no action"
        }
      },
      "compositePrimaryKeys": {},
      "uniqueConstraints": {},
      "policies": {},
      "checkConstraints": {},
      "isRLSEnabled": false
    },
    "public.system_config": {
      "name": "system_config",
      "schema": "",
      "columns": {
        "id": {
          "name": "id",
          "type": "serial",
          "primaryKey": true,
          "notNull": true
        },
        "config_key": {
          "name": "config_key",
          "type": "varchar(255)",
          "primaryKey": false,
          "notNull": true
        },
        "config_value": {
          "name": "config_value",
          "type": "json",
          "primaryKey": false,
          "notNull": true
        },
        "description": {
          "name": "description",
          "type": "text",
          "primaryKey": false,
          "notNull": false
        },
        "created_at": {
          "name": "created_at",
          "type": "timestamp",
          "primaryKey": false,
          "notNull": true,
          "default": "now()"
        },
        "updated_at": {
          "name": "updated_at",
          "type": "timestamp",
          "primaryKey": false,
          "notNull": true,
          "default": "now()"
        }
      },
      "indexes": {},
      "foreignKeys": {},
      "compositePrimaryKeys": {},
      "uniqueConstraints": {
        "system_config_config_key_unique": {
          "name": "system_config_config_key_unique",
          "nullsNotDistinct": false,
          "columns": [
            "config_key"
          ]
        }
      },
      "policies": {},
      "checkConstraints": {},
      "isRLSEnabled": false
    },
    "public.tokens": {
      "name": "tokens",
      "schema": "",
      "columns": {
        "id": {
          "name": "id",
          "type": "serial",
          "primaryKey": true,
          "notNull": true
        },
        "user_id": {
          "name": "user_id",
          "type": "integer",
          "primaryKey": false,
          "notNull": true
        },
        "balance": {
          "name": "balance",
          "type": "integer",
          "primaryKey": false,
          "notNull": true,
          "default": 0
        },
        "created_at": {
          "name": "created_at",
          "type": "timestamp",
          "primaryKey": false,
          "notNull": true,
          "default": "now()"
        },
        "updated_at": {
          "name": "updated_at",
          "type": "timestamp",
          "primaryKey": false,
          "notNull": true,
          "default": "now()"
        }
      },
      "indexes": {
        "tokens_user_idx": {
          "name": "tokens_user_idx",
          "columns": [
            {
              "expression": "user_id",
              "isExpression": false,
              "asc": true,
              "nulls": "last"
            }
          ],
          "isUnique": false,
          "concurrently": false,
          "method": "btree",
          "with": {}
        }
      },
      "foreignKeys": {
        "tokens_user_id_users_id_fk": {
          "name": "tokens_user_id_users_id_fk",
          "tableFrom": "tokens",
          "tableTo": "users",
          "columnsFrom": [
            "user_id"
          ],
          "columnsTo": [
            "id"
          ],
          "onDelete": "no action",
          "onUpdate": "no action"
        }
      },
      "compositePrimaryKeys": {},
      "uniqueConstraints": {
        "tokens_user_id_unique": {
          "name": "tokens_user_id_unique",
          "nullsNotDistinct": false,
          "columns": [
            "user_id"
          ]
        }
      },
      "policies": {},
      "checkConstraints": {},
      "isRLSEnabled": false
    },
    "public.token_transactions": {
      "name": "token_transactions",
      "schema": "",
      "columns": {
        "id": {
          "name": "id",
          "type": "serial",
          "primaryKey": true,
          "notNull": true
        },
        "user_id": {
          "name": "user_id",
          "type": "integer",
          "primaryKey": false,
          "notNull": true
        },
        "type": {
          "name": "type",
          "type": "transaction_type",
          "typeSchema": "public",
          "primaryKey": false,
          "notNull": true
        },
        "amount": {
          "name": "amount",
          "type": "integer",
          "primaryKey": false,
          "notNull": true
        },
        "cost": {
          "name": "cost",
          "type": "numeric(10, 2)",
          "primaryKey": false,
          "notNull": false
        },
        "reference_id": {
          "name": "reference_id",
          "type": "varchar(255)",
          "primaryKey": false,
          "notNull": false
        },
        "reference_type": {
          "name": "reference_type",
          "type": "varchar(100)",
          "primaryKey": false,
          "notNull": false
        },
        "payment_reference": {
          "name": "payment_reference",
          "type": "varchar(255)",
          "primaryKey": false,
          "notNull": false
        },
        "description": {
          "name": "description",
          "type": "text",
          "primaryKey": false,
          "notNull": false
        },
        "created_at": {
          "name": "created_at",
          "type": "timestamp",
          "primaryKey": false,
          "notNull": true,
          "default": "now()"
        }
      },
      "indexes": {
        "token_transactions_user_idx": {
          "name": "token_transactions_user_idx",
          "columns": [
            {
              "expression": "user_id",
              "isExpression": false,
              "asc": true,
              "nulls": "last"
            }
          ],
          "isUnique": false,
          "concurrently": false,
          "method": "btree",
          "with": {}
        },
        "token_transactions_type_idx": {
          "name": "token_transactions_type_idx",
          "columns": [
            {
              "expression": "type",
              "isExpression": false,
              "asc": true,
              "nulls": "last"
            }
          ],
          "isUnique": false,
          "concurrently": false,
          "method": "btree",
          "with": {}
        },
        "token_transactions_date_idx": {
          "name": "token_transactions_date_idx",
          "columns": [
            {
              "expression": "created_at",
              "isExpression": false,
              "asc": true,
              "nulls": "last"
            }
          ],
          "isUnique": false,
          "concurrently": false,
          "method": "btree",
          "with": {}
        }
      },
      "foreignKeys": {
        "token_transactions_user_id_users_id_fk": {
          "name": "token_transactions_user_id_users_id_fk",
          "tableFrom": "token_transactions",
          "tableTo": "users",
          "columnsFrom": [
            "user_id"
          ],
          "columnsTo": [
            "id"
          ],
          "onDelete": "no action",
          "onUpdate": "no action"
        }
      },
      "compositePrimaryKeys": {},
      "uniqueConstraints": {},
      "policies": {},
      "checkConstraints": {},
      "isRLSEnabled": false
    },
    "public.trips": {
      "name": "trips",
      "schema": "",
      "columns": {
        "id": {
          "name": "id",
          "type": "serial",
          "primaryKey": true,
          "notNull": true
        },
        "agent_id": {
          "name": "agent_id",
          "type": "integer",
          "primaryKey": false,
          "notNull": true
        },
        "title": {
          "name": "title",
          "type": "varchar(255)",
          "primaryKey": false,
          "notNull": true
        },
        "description": {
          "name": "description",
          "type": "text",
          "primaryKey": false,
          "notNull": false
        },
        "itinerary": {
          "name": "itinerary",
          "type": "text",
          "primaryKey": false,
          "notNull": false
        },
        "price": {
          "name": "price",
          "type": "numeric(10, 2)",
          "primaryKey": false,
          "notNull": true
        },
        "max_seats": {
          "name": "max_seats",
          "type": "integer",
          "primaryKey": false,
          "notNull": true
        },
        "available_seats": {
          "name": "available_seats",
          "type": "integer",
          "primaryKey": false,
          "notNull": true
        },
        "location": {
          "name": "location",
          "type": "varchar(255)",
          "primaryKey": false,
          "notNull": true
        },
        "start_date": {
          "name": "start_date",
          "type": "date",
          "primaryKey": false,
          "notNull": true
        },
        "end_date": {
          "name": "end_date",
          "type": "date",
          "primaryKey": false,
          "notNull": true
        },
        "status": {
          "name": "status",
          "type": "trip_status",
          "typeSchema": "public",
          "primaryKey": false,
          "notNull": true,
          "default": "'active'"
        },
        "average_rating": {
          "name": "average_rating",
          "type": "numeric(3, 2)",
          "primaryKey": false,
          "notNull": false,
          "default": "'0'"
        },
        "total_reviews": {
          "name": "total_reviews",
          "type": "integer",
          "primaryKey": false,
          "notNull": false,
          "default": 0
        },
        "images": {
          "name": "images",
          "type": "json",
          "primaryKey": false,
          "notNull": false
        },
        "created_at": {
          "name": "created_at",
          "type": "timestamp",
          "primaryKey": false,
          "notNull": true,
          "default": "now()"
        },
        "updated_at": {
          "name": "updated_at",
          "type": "timestamp",
          "primaryKey": false,
          "notNull": true,
          "default": "now()"
        },
        "deleted_at": {
          "name": "deleted_at",
          "type": "timestamp",
          "primaryKey": false,
          "notNull": false
        }
      },
      "indexes": {
        "trips_agent_idx": {
          "name": "trips_agent_idx",
          "columns": [
            {
              "expression": "agent_id",
              "isExpression": false,
              "asc": true,
              "nulls": "last"
            }
          ],
          "isUnique": false,
          "concurrently": false,
          "method": "btree",
          "with": {}
        },
        "trips_location_idx": {
          "name": "trips_location_idx",
          "columns": [
            {
              "expression": "location",
              "isExpression": false,
              "asc": true,
              "nulls": "last"
            }
          ],
          "isUnique": false,
          "concurrently": false,
          "method": "btree",
          "with": {}
        },
        "trips_status_idx": {
          "name": "trips_status_idx",
          "columns": [
            {
              "expression": "status",
              "isExpression": false,
              "asc": true,
              "nulls": "last"
            }
          ],
          "isUnique": false,
          "concurrently": false,
          "method": "btree",
          "with": {}
        },
        "trips_date_idx": {
          "name": "trips_date_idx",
          "columns": [
            {
              "expression": "start_date",
              "isExpression": false,
              "asc": true,
              "nulls": "last"
            }
          ],
          "isUnique": false,
          "concurrently": false,
          "method": "btree",
          "with": {}
        },
        "trips_price_idx": {
          "name": "trips_price_idx",
          "columns": [
            {
              "expression": "price",
              "isExpression": false,
              "asc": true,
              "nulls": "last"
            }
          ],
          "isUnique": false,
          "concurrently": false,
          "method": "btree",
          "with": {}
        }
      },
      "foreignKeys": {
        "trips_agent_id_users_id_fk": {
          "name": "trips_agent_id_users_id_fk",
          "tableFrom": "trips",
          "tableTo": "users",
          "columnsFrom": [
            "agent_id"
          ],
          "columnsTo": [
            "id"
          ],
          "onDelete": "no action",
          "onUpdate": "no action"
        }
      },
      "compositePrimaryKeys": {},
      "uniqueConstraints": {},
      "policies": {},
      "checkConstraints": {},
      "isRLSEnabled": false
    },
    "public.users": {
      "name": "users",
      "schema": "",
      "columns": {
        "id": {
          "name": "id",
          "type": "serial",
          "primaryKey": true,
          "notNull": true
        },
        "name": {
          "name": "name",
          "type": "varchar(255)",
          "primaryKey": false,
          "notNull": true
        },
        "email": {
          "name": "email",
          "type": "varchar(255)",
          "primaryKey": false,
          "notNull": true
        },
        "phone": {
          "name": "phone",
          "type": "varchar(20)",
          "primaryKey": false,
          "notNull": false
        },
        "password_hash": {
          "name": "password_hash",
          "type": "varchar(255)",
          "primaryKey": false,
          "notNull": true
        },
        "role": {
          "name": "role",
          "type": "user_role",
          "typeSchema": "public",
          "primaryKey": false,
          "notNull": true,
          "default": "'client'"
        },
        "status": {
          "name": "status",
          "type": "user_status",
          "typeSchema": "public",
          "primaryKey": false,
          "notNull": true,
          "default": "'active'"
        },
        "profile_image": {
          "name": "profile_image",
          "type": "text",
          "primaryKey": false,
          "notNull": false
        },
        "email_verified": {
          "name": "email_verified",
          "type": "boolean",
          "primaryKey": false,
          "notNull": true,
          "default": false
        },
        "created_at": {
          "name": "created_at",
          "type": "timestamp",
          "primaryKey": false,
          "notNull": true,
          "default": "now()"
        },
        "updated_at": {
          "name": "updated_at",
          "type": "timestamp",
          "primaryKey": false,
          "notNull": true,
          "default": "now()"
        },
        "deleted_at": {
          "name": "deleted_at",
          "type": "timestamp",
          "primaryKey": false,
          "notNull": false
        }
      },
      "indexes": {
        "users_email_idx": {
          "name": "users_email_idx",
          "columns": [
            {
              "expression": "email",
              "isExpression": false,
              "asc": true,
              "nulls": "last"
            }
          ],
          "isUnique": false,
          "concurrently": false,
          "method": "btree",
          "with": {}
        },
        "users_role_idx": {
          "name": "users_role_idx",
          "columns": [
            {
              "expression": "role",
              "isExpression": false,
              "asc": true,
              "nulls": "last"
            }
          ],
          "isUnique": false,
          "concurrently": false,
          "method": "btree",
          "with": {}
        },
        "users_status_idx": {
          "name": "users_status_idx",
          "columns": [
            {
              "expression": "status",
              "isExpression": false,
              "asc": true,
              "nulls": "last"
            }
          ],
          "isUnique": false,
          "concurrently": false,
          "method": "btree",
          "with": {}
        }
      },
      "foreignKeys": {},
      "compositePrimaryKeys": {},
      "uniqueConstraints": {
        "users_email_unique": {
          "name": "users_email_unique",
          "nullsNotDistinct": false,
          "columns": [
            "email"
          ]
        }
      },
      "policies": {},
      "checkConstraints": {},
      "isRLSEnabled": false
    }
  },
  "enums": {
    "public.payment_status": {
      "name": "payment_status",
      "schema": "public",
      "values": [
        "pending",
        "paid",
        "failed",
        "refunded"
      ]
    },
    "public.booking_status": {
      "name": "booking_status",
      "schema": "public",
      "values": [
        "pending",
        "confirmed",
        "cancelled",
        "completed"
      ]
    },
    "public.message_status": {
      "name": "message_status",
      "schema": "public",
      "values": [
        "new",
        "in_progress",
        "resolved",
        "closed"
      ]
    },
    "public.custom_trip_status": {
      "name": "custom_trip_status",
      "schema": "public",
      "values": [
        "pending",
        "assigned",
        "responded",
        "completed",
        "cancelled"
      ]
    },
    "public.application_status": {
      "name": "application_status",
      "schema": "public",
      "values": [
        "pending",
        "accepted",
        "rejected"
      ]
    },
    "public.job_status": {
      "name": "job_status",
      "schema": "public",
      "values": [
        "open",
        "closed",
        "filled"
      ]
    },
    "public.notification_type": {
      "name": "notification_type",
      "schema": "public",
      "values": [
        "booking",
        "cancellation",
        "job_update",
        "system"
      ]
    },
    "public.payment_status_enum": {
      "name": "payment_status_enum",
      "schema": "public",
      "values": [
        "pending",
        "completed",
        "failed",
        "refunded"
      ]
    },
    "public.review_status": {
      "name": "review_status",
      "schema": "public",
      "values": [
        "active",
        "hidden",
        "flagged"
      ]
    },
    "public.transaction_type": {
      "name": "transaction_type",
      "schema": "public",
      "values": [
        "purchase",
        "usage",
        "refund",
        "admin_grant"
      ]
    },
    "public.trip_status": {
      "name": "trip_status",
      "schema": "public",
      "values": [
        "active",
        "inactive",
        "deleted"
      ]
    },
    "public.user_role": {
      "name": "user_role",
      "schema": "public",
      "values": [
        "client",
        "agent",
        "admin"
      ]
    },
    "public.user_status": {
      "name": "user_status",
      "schema": "public",
      "values": [
        "active",
        "suspended",
        "deleted"
      ]
    }
  },
  "schemas": {},
  "sequences": {},
  "roles": {},
  "policies": {},
  "views": {},
  "_meta": {
    "columns": {},
    "schemas": {},
    "tables": {}
  }
}